oxtree/__init__.py
oxtree/main.py
oxtree-0.0.1.dist-info/METADATA
oxtree-0.0.1.dist-info/WHEEL
oxtree-0.0.1.dist-info/entry_points.txt
oxtree-0.0.1.dist-info/top_level.txt
oxtree-0.0.1.dist-info/RECORD
