Metadata-Version: 2.1
Name: oxtree
Version: 0.0.1
Summary: A Handy Script to view Directory Tree Structure
Author: 0x68616469
Keywords: tree,folder
Classifier: Development Status :: 4 - Beta
Classifier: Intended Audience :: Developers
Classifier: Programming Language :: Python :: 3
Classifier: Operating System :: Unix
Classifier: Operating System :: MacOS :: MacOS X
Classifier: Operating System :: Microsoft :: Windows
Requires-Dist: oxflags
